pyxmatlab/__init__.py
pyxmatlab-2024.3.2.dist-info/LICENSE
pyxmatlab-2024.3.2.dist-info/WHEEL
pyxmatlab-2024.3.2.dist-info/METADATA
pyxmatlab-2024.3.2.dist-info/RECORD
